{"pageProps":{"title":"What designer can do","date":"2022-05-10T20:31:59.889Z","category":["Trend"],"cover":"/images/blog/blog-image-1.jpg","thumb":"/images/blog/sm/blog-image-1.jpg","content":"\nBlanditiis corporis [Link Text](https://themeforest.net) accusamus accusamus. **Bold Text** sed quasi neque rerum deserunt eum sint ad. Et excepturi quia ut qui. Dolorem et et distinctio rerum. Eveniet suscipit eveniet recusandae. Vero qui _Italic Text_ quas aliquam. Expedita saepe non et velit voluptas `npm run install` quidem ut dignissimos. Et architecto ex et iste. Qui dolor sunt magnam eos mollitia. Delectus voluptas sed ut et blanditiis. Quos perferendis distinctio dolor eligendi. Sequi dolores velit et at inventore vero culpa similique.\n\n##### Dolorem et et distinctio rerum.\n\nEveniet suscipit eveniet recusandae. Vero qui quas aliquam. Expedita saepe non et velit voluptas quidem ut dignissimos. Labore odio deserunt deserunt ipsam omnis ut. Consequatur aut eos voluptas harum cumque explicabo dicta.\n\n> Eaque minus aut voluptatum. Aut beatae numquam similique quasi. Est perferendis voluptatem qui sint ut veritatis inventore. Quaerat repudiandae deleniti asperiores mollitia rerum voluptate.\n\nAd reprehenderit accusamus. Incidunt architecto rerum rerum maxime est. Exercitationem harum autem quam id sed consequatur possimus. Distinctio asperiores nostrum consectetur minima velit est amet quas modi. Labore odio deserunt deserunt ipsam omnis ut. Consequatur aut eos voluptas harum cumque explicabo dicta.\n\n```\nconst getSinglePostData = (slug) => {\n    const article = fs.readFileSync(\n        path.join(process.cwd(), \"src/articles\", slug + \".md\"),\n        \"utf-8\"\n    );\n    const { data: frontmatter, content } = matter(article);\n    return {\n        frontmatter,\n        content,\n    };\n};\n```\n\nAd reprehenderit accusamus. Incidunt architecto rerum rerum maxime est. Exercitationem harum autem quam id sed consequatur possimus. Distinctio asperiores nostrum consectetur minima velit est amet quas modi. Labore odio deserunt deserunt ipsam omnis ut. Consequatur aut eos voluptas harum cumque explicabo dicta.\n\n##### Nested Order List\n\n1. First item\n2. Second item\n    1. Nested First item\n    2. Nested Second item\n3. Third item\n\n##### Nested Unorder List\n\n-   First item\n-   Second item\n    -   Nested First item\n    -   Nested Second item\n-   Third item\n\nEt excepturi quia ut qui. Dolorem et et distinctio rerum. Eveniet suscipit eveniet recusandae. Vero qui quas aliquam. Expedita saepe non et velit voluptas quidem ut dignissimos. Et architecto ex et iste. Qui dolor sunt magnam eos mollitia. Delectus voluptas sed ut et blanditiis.\n"},"__N_SSG":true}